setup.py
bin/vint
vint/__init__.py
vint/cerf_api.py
vint/file_util.py
vint/misc.py
vint/vint.py
vint.egg-info/PKG-INFO
vint.egg-info/SOURCES.txt
vint.egg-info/dependency_links.txt
vint.egg-info/requires.txt
vint.egg-info/top_level.txt