Metadata-Version: 1.1
Name: vint
Version: 0.1.3
Summary: Cerf exam service client to let the applicant to start/finish the exam
Home-page: http://tchen.me
Author: Tyr Chen
Author-email: tyr.chen@gmail.com
License: MIT
Download-URL: https://github.com/tyrchen/vint
Keywords: python cerf exam
Platform: UNKNOWN
Classifier: Intended Audience :: Developers
Classifier: Natural Language :: English
Classifier: Development Status :: 3 - Alpha
Classifier: License :: OSI Approved :: MIT License
Classifier: Programming Language :: Python
Classifier: Programming Language :: Python :: 2
Classifier: Programming Language :: Python :: 2.6
Classifier: Programming Language :: Python :: 2.7
